admin_multilanguage/__init__.py
admin_multilanguage/apps.py
admin_multilanguage/urls.py
admin_multilanguage/views.py
admin_multilanguage/__pycache__/__init__.cpython-36.pyc
admin_multilanguage/__pycache__/urls.cpython-36.pyc
admin_multilanguage/__pycache__/views.cpython-36.pyc
admin_multilanguage/templates/admin/base_site.html
django_admin_multilang-1.0.6.dist-info/LICENSE
django_admin_multilang-1.0.6.dist-info/METADATA
django_admin_multilang-1.0.6.dist-info/WHEEL
django_admin_multilang-1.0.6.dist-info/top_level.txt
django_admin_multilang-1.0.6.dist-info/RECORD
