Metadata-Version: 2.1
Name: django-admin-multilang
Version: 1.0.6
Summary: A very simple Django application that adds the ability on the admin page to select a language manually.
Home-page: https://github.com/Vadim-Karpenko/django-admin-multilang
Author: Karpenko Vadim
Author-email: j.rell@protonmail.com
License: UNKNOWN
Platform: UNKNOWN
Classifier: Programming Language :: Python :: 3
Classifier: License :: OSI Approved :: MIT License
Classifier: Operating System :: OS Independent
